handtokening/__init__.py
handtokening/admin.py
handtokening/asgi.py
handtokening/clients/__init__.py
handtokening/clients/admin.py
handtokening/clients/apps.py
handtokening/clients/authentication.py
handtokening/clients/management/__init__.py
handtokening/clients/management/commands/__init__.py
handtokening/clients/management/commands/client_secret.py
handtokening/clients/migrations/0001_initial.py
handtokening/clients/migrations/0002_rotate_every_non_nullable.py
handtokening/clients/migrations/0003_reworksecret.py
handtokening/clients/migrations/__init__.py
handtokening/clients/models.py
handtokening/clients/templates/clients/secrets-generated.html
handtokening/clients/tests/__init__.py
handtokening/clients/tests/test_middleware.py
handtokening/clients/views.py
handtokening/settings/__init__.py
handtokening/settings/base.py
handtokening/settings/local.py
handtokening/settings/prod.py
handtokening/settings/util.py
handtokening/signing/__init__.py
handtokening/signing/admin.py
handtokening/signing/apps.py
handtokening/signing/conf.py
handtokening/signing/external_value.py
handtokening/signing/management/__init__.py
handtokening/signing/management/commands/__init__.py
handtokening/signing/management/commands/add_timestamp_server.py
handtokening/signing/management/commands/set_up_test_signing.py
handtokening/signing/migrations/0001_initial.py
handtokening/signing/migrations/0002_profile_access.py
handtokening/signing/migrations/0003_osslcommand.py
handtokening/signing/migrations/0004_version_column.py
handtokening/signing/migrations/0005_virustotal.py
handtokening/signing/migrations/0006_engine_version_nullable.py
handtokening/signing/migrations/0007_remove_certificate_ossl_provider.py
handtokening/signing/migrations/__init__.py
handtokening/signing/models.py
handtokening/signing/osslsigncode.py
handtokening/signing/serializers.py
handtokening/signing/templates/signing/vt_results_table.html
handtokening/signing/tests/__init__.py
handtokening-1.0.2.dist-info/WHEEL
handtokening-1.0.2.dist-info/METADATA
handtokening-1.0.2.dist-info/RECORD
