Metadata-Version: 2.4
Name: handtokening
Version: 1.0.2
Summary: Code-signing server built in Python/Django
Author: Dexter Castor Döpping
Author-email: Dexter Castor Döpping <dexter.c.dopping@gmail.com>
License-Expression: AGPL-3.0-only
Requires-Dist: asn1crypto~=1.5
Requires-Dist: django~=5.2
Requires-Dist: django-ipware~=7.0
Requires-Dist: djangorestframework~=3.16
Requires-Dist: vt-py~=0.21
Requires-Python: >=3.13
Project-URL: Issues, https://github.com/dextercd/Handtokening/issues
Project-URL: Repository, https://github.com/dextercd/Handtokening
